{
    "drive_id": "889478",
    "domain_id": "bj29",
    "file_id": "xxxxxxxxxxxxxxx",
    "name": "test",
    "type": "folder",
    "created_at": "2021-11-10T05:50:55.543Z",
    "updated_at": "2021-11-10T05:50:55.543Z",
    "hidden": false,
    "starred": false,
    "status": "available",
    "user_meta": "{\"client\":\"web\"}",
    "parent_file_id": "root",
    "encrypt_mode": "none",
    "creator_type": "User",
    "creator_id": "xxxxxxxxxxxxxxxxxx",
    "last_modifier_type": "User",
    "last_modifier_id": "xxxxxxxxxxxxxxxxx",
    "trashed": false
}